reflex_monaco/__init__.py
reflex_monaco/monaco.py
reflex_monaco-0.0.2.dist-info/METADATA
reflex_monaco-0.0.2.dist-info/WHEEL
reflex_monaco-0.0.2.dist-info/top_level.txt
reflex_monaco-0.0.2.dist-info/RECORD
