Metadata-Version: 2.2
Name: reflex-monaco
Version: 0.0.2
Summary: A package wrapping Monaco Editor for Reflex
Author-email: Lendemor <thomas.brandeho@gmail.com>
License: Apache-2.0
Project-URL: homepage, https://monaco-demo.reflex.run/
Project-URL: source, https://github.com/Lendemor/reflex-monaco
Keywords: reflex,reflex-custom-components,monaco,editor,vscode
Classifier: Development Status :: 4 - Beta
Requires-Python: >=3.8
Requires-Dist: reflex>=0.5.0
Provides-Extra: dev
Requires-Dist: build; extra == "dev"
Requires-Dist: twine; extra == "dev"
